<!-- 
  事象:
    旧Style系要素（この例では GridStyle）に含まれるマイグレート対象の属性が、StyleXML に移動した後も古いままです。

  備考:
    各種変換ステップが LayoutXML しか対象にしていないため、StyleXML に抽出済みのXMLが手付かずになるようです。
  
  経過:
    - 2025-09-04: 何らかの加工が行われるようになったことを確認できたため一応FIXED。
      変更内容自体があまり正しくないが、それらについては個別に別ケースを起票
-->

<LayoutXml>
  <LinearLayout>
    <LayoutBody>

      <Grid cols="30" rows="10">
        <GridStyle outerBorderTopThickness="1" />
        <GridCell col="0" row="0">
          <Text>text</Text>
        </GridCell>
      </Grid>

      <Spacer height="10" />

      <Grid cols="30" rows="10">
        <GridStyle borderColor="rgb(0,0,0)" />
        <GridCell col="0" row="0">
          <Text>text</Text>
        </GridCell>
      </Grid>

      <Spacer height="10" />

      <Grid cols="30" rows="10">
        <GridStyle borderStyle="dasharray(1,2)" />
        <GridCell col="0" row="0">
          <Text>text</Text>
        </GridCell>
      </Grid>

    </LayoutBody>
  </LinearLayout>
</LayoutXml>